.gitignore
LICENCE.txt
MANIFEST.in
README.rst
setup.py
Sveetchies/BatchDirCovers.py
Sveetchies/DocExport.py
Sveetchies/ToExcel.py
Sveetchies/TreeMaker.py
Sveetchies/__init__.py
Sveetchies/utils.py
Sveetchies.egg-info/PKG-INFO
Sveetchies.egg-info/SOURCES.txt
Sveetchies.egg-info/dependency_links.txt
Sveetchies.egg-info/not-zip-safe
Sveetchies.egg-info/requires.txt
Sveetchies.egg-info/top_level.txt
Sveetchies/BatchMediasDir/__init__.py
Sveetchies/BatchMediasDir/frontend.py
Sveetchies/BatchMediasDir/manager.py
Sveetchies/BatchMediasDir/models.py
Sveetchies/BatchMediasDir/modules.py
Sveetchies/chan/__init__.py
Sveetchies/chan/cli.py
Sveetchies/chan/parser.py
Sveetchies/cli/DjangoCLI.py
Sveetchies/cli/ImportDjangoProject.py
Sveetchies/cli/SveePyCLI.py
Sveetchies/cli/SveePyCLI_Old.py
Sveetchies/cli/__init__.py
Sveetchies/cli/inputs.py
Sveetchies/cli/termcolors.py
Sveetchies/django/TreeMaker.py
Sveetchies/django/__init__.py
Sveetchies/django/auth.py
Sveetchies/django/context_processors.py
Sveetchies/django/filefield.py
Sveetchies/django/response.py
Sveetchies/django/search.py
Sveetchies/django/attachments/__init__.py
Sveetchies/django/attachments/admin.py
Sveetchies/django/attachments/managers.py
Sveetchies/django/attachments/models.py
Sveetchies/django/attachments/utils.py
Sveetchies/django/attachments/templates/attachments/attachments_widget.html
Sveetchies/django/attachments/templatetags/__init__.py
Sveetchies/django/attachments/templatetags/attachments_tags.py
Sveetchies/django/autobreadcrumbs/__init__.py
Sveetchies/django/autobreadcrumbs/context_processors.py
Sveetchies/django/autobreadcrumbs/decorators.py
Sveetchies/django/autobreadcrumbs/models.py
Sveetchies/django/autobreadcrumbs/management/__init__.py
Sveetchies/django/autobreadcrumbs/management/commands/__init__.py
Sveetchies/django/autobreadcrumbs/management/commands/breadcrumbs.py
Sveetchies/django/autobreadcrumbs/templates/autobreadcrumbs_tag.html
Sveetchies/django/autobreadcrumbs/templatetags/__init__.py
Sveetchies/django/autobreadcrumbs/templatetags/autobreadcrumb.py
Sveetchies/django/djangocodemirror/__init__.py
Sveetchies/django/djangocodemirror/fields.py
Sveetchies/django/djangocodemirror/models.py
