Metadata-Version: 1.1
Name: Sveetchies
Version: 1.8.9.4
Summary: 
